pyhelp/HELP3O.cp37-win_amd64.pyd
pyhelp/__init__.py
pyhelp/bilan.py
pyhelp/managers.py
pyhelp/output.py
pyhelp/preprocessing.py
pyhelp/processing.py
pyhelp/utils.py
pyhelp/weather_reader.py
pyhelp/scripts/__init__.py
pyhelp/scripts/download_solrad_data_from_cds.py
pyhelp/scripts/example_pyhelp_calc_yearly_values.py
pyhelp/scripts/example_pyhelp_outputs_v0.3.py
pyhelp/scripts/grid_data_extractor.py
pyhelp/scripts/postprocess_tair_moy.py
pyhelp/scripts/produce_meteo_maps.py
pyhelp/tests/__init__.py
pyhelp/tests/test_help3o.py
pyhelp/tests/test_helpmanager.py
pyhelp/tests/test_read_input_files.py
pyhelp-0.4.0.dist-info/LICENSE
pyhelp-0.4.0.dist-info/METADATA
pyhelp-0.4.0.dist-info/WHEEL
pyhelp-0.4.0.dist-info/top_level.txt
pyhelp-0.4.0.dist-info/RECORD
