Metadata-Version: 2.1
Name: pyhelp
Version: 0.4.0
Summary: A Python library for the assessment of spatially distributed groundwater recharge and hydrological components with HELP.
Home-page: https://github.com/cgq-qgc/pyhelp
Author: PyHELP Project Contributors
Author-email: jean-sebastien.gosselin@ete.inrs.ca
License: MIT
Platform: UNKNOWN
Classifier: License :: OSI Approved :: MIT License
Classifier: Operating System :: Microsoft :: Windows
Classifier: Programming Language :: Python :: 3.7
Classifier: Programming Language :: Python :: 3.8
Classifier: Programming Language :: Python :: 3.9
Classifier: Intended Audience :: Science/Research
Classifier: Intended Audience :: Education
Classifier: Topic :: Scientific/Engineering
Requires-Dist: numpy
Requires-Dist: scipy
Requires-Dist: pandas
Requires-Dist: h5py (>=3)
Requires-Dist: matplotlib
